zero-shot-re/__init__.py
zero-shot-re/extractor.py
zero_shot_re/__init__.py
zero_shot_re/extractor.py
zero_shot_re/model.py
zero_shot_re/test_pretrained.py
zero_shot_re-0.0.4.dist-info/METADATA
zero_shot_re-0.0.4.dist-info/WHEEL
zero_shot_re-0.0.4.dist-info/top_level.txt
zero_shot_re-0.0.4.dist-info/RECORD
